stepper/__init__.py
stepper/__main__.py
micropython_stepper-1.0.3.dist-info/LICENSE
micropython_stepper-1.0.3.dist-info/METADATA
micropython_stepper-1.0.3.dist-info/WHEEL
micropython_stepper-1.0.3.dist-info/top_level.txt
micropython_stepper-1.0.3.dist-info/RECORD
