Metadata-Version: 2.1
Name: micropython-stepper
Version: 1.0.3
Summary: Library to use stepper drivers in micropython in a tidy way
Author-email: redoxcode <redoxcode@github.com>
License: MIT License
Project-URL: Homepage, https://github.com/redoxcode/micropython-stepper
Keywords: stepper,motor
Classifier: License :: OSI Approved :: MIT License
Classifier: Programming Language :: Python :: Implementation :: MicroPython
Provides-Extra: dev
License-File: LICENSE
